{
  "sheetName": "171214",
  "identity": "171214C",
  "crossEntries": [
    {
      "row": 1,
      "number": 1,
      "text": "బడి చేతకాకపొతే మంత్రగాళ్ళు చేసేది (4)"
    },
    {
      "row": 2,
      "number": 2,
      "text": "హిమాలయాల్లో విశేషంగా అప్పుడప్పుడు కనిపించే మోసకాడు (3)"
    },
    {
      "row": 3,
      "number": 9,
      "text": "రాత్రి ఉండే ఇల్లు (3)"
    },
    {
      "row": 4,
      "number": 10,
      "text": "న...నర సేవా? కాదు కోతిమూక (5)"
    },
    {
      "row": 5,
      "number": 11,
      "text": "గొప్ప శక్తి కలిగిన సీసము (5)"
    },
    {
      "row": 6,
      "number": 13,
      "text": "కుర్ర కుంక ముదముతో విర్రవీగితే ఉల్లిగడ్డలా మారుతుంది (5)"
    },
    {
      "row": 7,
      "number": 15,
      "text": "వీరత్వం మధ్యన ఉంటే వేడి పుడుతుంది (5)"
    },
    {
      "row": 8,
      "number": 17,
      "text": "కండ కలవాడికే తియ్యపదార్థం దొరుకుతుంది (4)"
    },
    {
      "row": 9,
      "number": 21,
      "text": "గారాబము మధ్యలో నస పిచ్చిగా పెడితే ప్రకటన (4)"
    },
    {
      "row": 10,
      "number": 23,
      "text": "ఒక భాషనుండి ఇంకొక భాషలో చెప్పు తగవు (5)"
    },
    {
      "row": 11,
      "number": 25,
      "text": "సమ్మతి మధ్య మరు మార్పు జరిగితే పక్షులకూత వినిపిస్తుంది (5)"
    },
    {
      "row": 12,
      "number": 27,
      "text": "తురక పోగు వేసుకుంటే ఎంతసేపైనా పడుక్కుంటాడు (5)"
    },
    {
      "row": 13,
      "number": 30,
      "text": "ప్రభువుల రథాలు సాగే త్రోవ (5)"
    },
    {
      "row": 14,
      "number": 31,
      "text": "ఎర్రని ముక్కూ కాళ్ళూ కల శ్రేష్ఠమైన పక్షి వికృతి రూపం (3)"
    },
    {
      "row": 15,
      "number": 32,
      "text": "ఏమీతెలియని అమాయకుడు (3)"
    },
    {
      "row": 16,
      "number": 33,
      "text": "చదువులతల్లి మాయ? కాదు, సాక్షాత్తూ విష్ణుమూర్తి (4)"
    }
  ],
  "downEntries": [
    {
      "row": 1,
      "number": 1,
      "text": "ఈ భాగోతం అంటే వృధాప్రయాస కాబోలు (2,3)"
    },
    {
      "row": 2,
      "number": 2,
      "text": "భిక్షాన్నపు ముద్ద తినే బకము ధవళమా? (7)"
    },
    {
      "row": 3,
      "number": 3,
      "text": "వినయవతిలో అప్పుడప్పుడు ఎగిరేది (3)"
    },
    {
      "row": 4,
      "number": 4,
      "text": "23 అడ్డంలో కద మార్పు జరిగితే వేదభాగం (5)"
    },
    {
      "row": 5,
      "number": 5,
      "text": "3o....................2☎ (6)"
    },
    {
      "row": 6,
      "number": 6,
      "text": "ఆ ఫలరసము నలుగురూ కూర్చొని తాగే కల్లు దుకాణం (5)"
    },
    {
      "row": 7,
      "number": 7,
      "text": "మరి తు చ తప్పకుండా ఇట్నుంచి నరుక్కురావడమే యోగ్యత అంటే. (4)"
    },
    {
      "row": 8,
      "number": 8,
      "text": "అసందర్భంగా అష్టావధాన ప్రక్రియలో అడిగేదా? (6)"
    },
    {
      "row": 9,
      "number": 12,
      "text": "అక్షరాలు చెక్కిన ఉంగరము ఆమోదాన్నిస్తుంది (3)"
    },
    {
      "row": 10,
      "number": 14,
      "text": "మొక్కజొన్న పంట ఊడ్చెస్తే మిగిలిన కాల విశేషం (2)"
    },
    {
      "row": 11,
      "number": 16,
      "text": "వృక్షవిశేషమైన వేదభాగం (3)"
    },
    {
      "row": 12,
      "number": 18,
      "text": "అంగవస్త్రంతో అడ్డుదూలం (3)"
    },
    {
      "row": 13,
      "number": 19,
      "text": "ఈ సంబరం - ముని కాపు మిన్న (3,3)"
    },
    {
      "row": 14,
      "number": 20,
      "text": "కలంతో చెయ్యి శిల (2)"
    },
    {
      "row": 15,
      "number": 22,
      "text": "పెళ్ళి జరుగు సుముహూర్తంలో వధువు ధరించేది (3)"
    },
    {
      "row": 16,
      "number": 23,
      "text": "“చలో, కనుడు” అనే మాటలో పరమార్థం పరమాత్మకే తెలియాలి (7) ఆ"
    },
    {
      "row": 17,
      "number": 24,
      "text": "తొక్కిన వెంటనే మోహం పుట్టించే ఔషధం కోసం, మా మతం గిరులు కదపడమే. (6)"
    },
    {
      "row": 18,
      "number": 25,
      "text": "అతివ రామ దర్శనంతో స్వర్గపురి చేరింది (5)"
    },
    {
      "row": 19,
      "number": 26,
      "text": "పిల్లలపట్ల ప్రేముంటే తల్లిదండ్రులు తీర్చేవి (2-3)"
    },
    {
      "row": 20,
      "number": 28,
      "text": "ఇది రేపుని లేకుండా చేసే యుగాంతం (4)"
    },
    {
      "row": 21,
      "number": 29,
      "text": "ఉషకి మధ్యలో ఉద్యోగం దొరికి చివరి ఎత్తుతో వేదాంత గ్రంథం కనిపించింది (5)"
    },
    {
      "row": 22,
      "number": 31,
      "text": "రామవరములో అప్పుడప్పుడు వినిపించే ధ్వని (3)"
    }
  ]
}