{
  "sheetName": "220668",
  "identity": "220668C",
  "crossEntries": [
    {
      "row": 1,
      "number": 1,
      "text": "మంత్రి తండ్రిగారు (3)"
    },
    {
      "row": 2,
      "number": 3,
      "text": "అంతులేని వేలవేలు (2)"
    },
    {
      "row": 3,
      "number": 4,
      "text": "ఉరమరగా శివుని భార్య (2)"
    },
    {
      "row": 4,
      "number": 6,
      "text": "ఎవరూ పుట్టించలేదు (3)"
    },
    {
      "row": 5,
      "number": 8,
      "text": "బంగారు బల్లెం (4)"
    },
    {
      "row": 6,
      "number": 10,
      "text": "20 శతక క్షేత్రము (4)"
    },
    {
      "row": 7,
      "number": 11,
      "text": "తెలుగు దిక్కు (2)"
    },
    {
      "row": 8,
      "number": 13,
      "text": "పురాణము (5)"
    },
    {
      "row": 9,
      "number": 16,
      "text": "మూల అడవి (2)"
    },
    {
      "row": 10,
      "number": 17,
      "text": "టవూటినీ (2)"
    },
    {
      "row": 11,
      "number": 18,
      "text": "కర్ణాటసుతాంధ్రపురుష (2)"
    },
    {
      "row": 12,
      "number": 20,
      "text": "స్తుతమతి అయిన ఆంధ్రకవి (3)"
    },
    {
      "row": 13,
      "number": 21,
      "text": "వడలిపోవు పురుషుడు (2)"
    },
    {
      "row": 14,
      "number": 23,
      "text": "కష్టజీవికి ఇరువైపులా ఉండాల్సినవాడు (2)"
    },
    {
      "row": 15,
      "number": 24,
      "text": "ఆకురసం వన్నె గల పాము (4)"
    },
    {
      "row": 16,
      "number": 26,
      "text": "జూదరి (4)"
    },
    {
      "row": 17,
      "number": 27,
      "text": "రెండింతలైతే నవ్వు (2)"
    },
    {
      "row": 18,
      "number": 29,
      "text": "31, 62 తో కలిసి ముక్తికి సాధానాలు (3)"
    },
    {
      "row": 19,
      "number": 31,
      "text": "29 చూడుడు (3)"
    },
    {
      "row": 20,
      "number": 32,
      "text": "మహాభారతం మొదటిపేరు (2)"
    },
    {
      "row": 21,
      "number": 33,
      "text": "గాలివానకు చెల్లాచెదురైన మొలకలు (4)"
    },
    {
      "row": 22,
      "number": 36,
      "text": "మదిదప్పిన మొదటివేల్పుకు మనుచరిత్ర విశేషణం (2)"
    },
    {
      "row": 23,
      "number": 37,
      "text": "స్వాధీనం (2)"
    },
    {
      "row": 24,
      "number": 38,
      "text": "నీరాట, వనాటములకు ఇది ఎట్లు కలిగింది? (4)"
    },
    {
      "row": 25,
      "number": 40,
      "text": "హంస (4)"
    },
    {
      "row": 26,
      "number": 41,
      "text": "చితపండూ (3)"
    },
    {
      "row": 27,
      "number": 42,
      "text": "పనుల వలన కీడు (4)"
    }
  ],
  "downEntries": [
    {
      "row": 1,
      "number": 13,
      "text": "సగం సందేహం (4)"
    },
    {
      "row": 2,
      "number": 14,
      "text": "తడి (2)"
    },
    {
      "row": 3,
      "number": 15,
      "text": "తలాతోకా లేని నియమము (2)"
    },
    {
      "row": 4,
      "number": 47,
      "text": "సంస్కృత సమాసాలపై తిరగబడిన తెలుగుకవి (4)"
    },
    {
      "row": 5,
      "number": 49,
      "text": "చెదిరిన స్వప్నం అబద్ధం (2)"
    },
    {
      "row": 6,
      "number": 50,
      "text": "రాజశేఖర చరిత్ర రచయిత (3)"
    },
    {
      "row": 7,
      "number": 51,
      "text": "ముల్భగప (3)"
    },
    {
      "row": 8,
      "number": 53,
      "text": "వెనుదిరిగిన స్వర్గం (2)"
    },
    {
      "row": 9,
      "number": 54,
      "text": "మెరుపు (4)"
    },
    {
      "row": 10,
      "number": 57,
      "text": "గొప్ప (4)"
    },
    {
      "row": 11,
      "number": 59,
      "text": "మాలినిసిగలో చీకటి (2)"
    },
    {
      "row": 12,
      "number": 61,
      "text": "18 కాదు (2)"
    },
    {
      "row": 13,
      "number": 2,
      "text": "29 చూడుడు (3)"
    },
    {
      "row": 14,
      "number": 54,
      "text": "21కి గౌరవం (2)"
    },
    {
      "row": 15,
      "number": 5,
      "text": "మేదినీ (2)"
    },
    {
      "row": 16,
      "number": 1,
      "text": "భూభారం మోసేవారు (7)"
    },
    {
      "row": 17,
      "number": 2,
      "text": "నడుం విరిగినా బ్రతుకు దీనికోసమే (2)"
    },
    {
      "row": 18,
      "number": 3,
      "text": "తెలుగువారి దేవుడు (3)"
    },
    {
      "row": 19,
      "number": 5,
      "text": "అరబ్బుల నివాస స్థలము (3)"
    },
    {
      "row": 20,
      "number": 6,
      "text": "శుభం (2)"
    },
    {
      "row": 21,
      "number": 7,
      "text": "కవుల కొలువు (7)"
    },
    {
      "row": 22,
      "number": 9,
      "text": "అఘమర్షణ మంత్రం (4)"
    },
    {
      "row": 23,
      "number": 12,
      "text": "అటునుండి పాము ఊపిరి (2)"
    },
    {
      "row": 24,
      "number": 14,
      "text": "పొడిగా రాత్రిధూపం (2)"
    },
    {
      "row": 25,
      "number": 15,
      "text": "ఆటకత్తె (2)"
    },
    {
      "row": 26,
      "number": 16,
      "text": "ఈ మధ్య కట్టుకోకపోయినా వక్త్రమే (2)"
    },
    {
      "row": 27,
      "number": 18,
      "text": "నల్ల చూర్ణము (2)"
    },
    {
      "row": 28,
      "number": 19,
      "text": "సరిగములలో ఐశ్వర్యం (3)"
    },
    {
      "row": 29,
      "number": 21,
      "text": "ఏనుగు (3)"
    },
    {
      "row": 30,
      "number": 22,
      "text": "విభక్తి ప్రత్యయాలు (2)"
    },
    {
      "row": 31,
      "number": 25,
      "text": "చూడము (3)"
    },
    {
      "row": 32,
      "number": 26,
      "text": "హస్తగతం (3)"
    },
    {
      "row": 33,
      "number": 28,
      "text": "కలం కారితే (5)"
    },
    {
      "row": 34,
      "number": 30,
      "text": "ఎద్దుతో స్వస్థత చేకూరిన కవి (5)"
    },
    {
      "row": 35,
      "number": 31,
      "text": "వినదగినది (5)"
    },
    {
      "row": 36,
      "number": 32,
      "text": "చెల్లాచెదురైన నీటిముల్లు (5)"
    },
    {
      "row": 37,
      "number": 34,
      "text": "మొండికేసే ఆఫ్రికాదేశం (3)"
    },
    {
      "row": 38,
      "number": 35,
      "text": "గొల్లుమన్న సూటిరేఖ (3)"
    },
    {
      "row": 39,
      "number": 38,
      "text": "తెలుగుల పుణ్యపేటి (3)"
    },
    {
      "row": 40,
      "number": 39,
      "text": "తెలంగాణాలో ఇకరారు (3)"
    },
    {
      "row": 41,
      "number": 43,
      "text": "ఈయనను పోలు పండితులు పృథ్విలో లేరట (7)"
    },
    {
      "row": 42,
      "number": 44,
      "text": "చిల్లు కానీ నాణెం (3)"
    },
    {
      "row": 43,
      "number": 46,
      "text": "అలవాటుపడు (3)"
    },
    {
      "row": 44,
      "number": 48,
      "text": "త్పృవ్వట బాబా కవి (7)"
    },
    {
      "row": 45,
      "number": 50,
      "text": "మెలిక పడిన గుదికాలు (3)"
    },
    {
      "row": 46,
      "number": 52,
      "text": "అలమర (3)"
    },
    {
      "row": 47,
      "number": 55,
      "text": "ముభలా (2)"
    },
    {
      "row": 48,
      "number": 56,
      "text": "అటునుండి తిరగడం (4)"
    },
    {
      "row": 49,
      "number": 58,
      "text": "ప్రత్యయం లేని చెట్టు (2)"
    },
    {
      "row": 50,
      "number": 60,
      "text": "నరము (2)"
    },
    {
      "row": 51,
      "number": 62,
      "text": "వాత పెట్టాలంటే ఇది కీలకం (2)"
    },
    {
      "row": 52,
      "number": 63,
      "text": "వడ్లచిలుక (2)"
    },
    {
      "row": 53,
      "number": 65,
      "text": "వెల (2)"
    },
    {
      "row": 54,
      "number": 67,
      "text": "పైన వేసుకొనేది (3)"
    },
    {
      "row": 55,
      "number": 68,
      "text": "తలకిందులైన కొలువులు (3)"
    },
    {
      "row": 56,
      "number": 70,
      "text": "ఆగిపోయిన అరబ్బీ దూత (2)"
    },
    {
      "row": 57,
      "number": 72,
      "text": "కిందినుంచి దున్నితే ఒక నాగలి భూమి (2)"
    }
  ]
}